Metadata-Version: 1.0
Name: coretemp
Version: 0.1
Summary: lightweight service to monitor CPU temp
Home-page: https://github.com/mmcbride1/python-coretemp
Author: Matthew R McBride
Author-email: mrmcbride@smcm.edu
License: UNKNOWN
Platform: UNKNOWN
